{
  "id": "f6b2377c9073",
  "title": "The Need to Read",
  "link": "http://www.paulgraham.com/read.html",
  "summary": "",
  "published": null,
  "source": "paulgraham.com",
  "source_url": "https://paulgraham.com",
  "summary_cn": "保罗·格雷厄姆（Paul Graham）在其文章《阅读的必要性》（The Need to Read）中，深入探讨了阅读及其衍生的写作能力在知识获取、思想生成和深度思考中的不可替代作用。\n\n文章开篇指出，科幻作品中通过“磁带”或其他高效方式将知识直接载入大脑，从而取代阅读的设想，不仅在短期内难以实现，即便实现了，也将是不足够的。作者的核心观点是，阅读的价值远不止于获取特定信息，它更重要的是能够教会人们如何写作。\n\n文章强调，写作并非仅仅是传达已有的思想，而是一个主动产生和发展思想的过程。优秀的写作者在动笔过程中，几乎总能发现新的、先前未曾意识到的观点或洞见。这种通过写作进行的“发现”是无可替代的。尽管与他人讨论是发展思想的良好方式，但在真正坐下来写作时，人们往往能进一步深化理解、激发出新的思考。作者明确提出，存在一种独特的思维方式，只能通过写作来实现。他承认，并非所有问题都需要写作来解决（例如简单的机械组装），但对于需要深入探究、复杂且连贯的思考，写作是不可或缺的工具。\n\n文章的关键概念在于区分了“传达思想”和“拥有/生成思想”两种功能，并强调写作在后者中的核心作用。它指出，被动的知识接收（如科幻中的“信息输入”）无法替代主动的、生成性的思维过程，而阅读和写作正是实现这一过程的基石。\n\n总之，格雷厄姆的结论是，阅读和写作不仅仅是获取和传递信息的手段，它们更是人类进行深度思考、发现新知、构建复杂思想的根本途径。在信息爆炸的时代，主动的阅读和写作能力对于培养批判性思维和原创性思想仍然至关重要，它们是任何形式的被动知识输入都无法取代的，是智能发展和思想创造的核心。"
}